portfly.py
portfly-0.36.dist-info/METADATA
portfly-0.36.dist-info/WHEEL
portfly-0.36.dist-info/licenses/LICENSE
portfly-0.36.dist-info/RECORD
