Metadata-Version: 2.1
Name: portfly
Version: 0.36
Summary: Remote/Local port forwarding in Python by TCP/UDP
Project-URL: homepage, https://github.com/xinlin-z/portfly
Author: xinlin-z
License: MIT License
License-File: LICENSE
Keywords: local,port forwarding,remote,tcp,udp
Classifier: License :: OSI Approved :: MIT License
Classifier: Operating System :: OS Independent
Classifier: Programming Language :: Python :: 3
Requires-Python: >=3.8
